MANIFEST.in
README.rst
setup.py
docs/HISTORY.txt
docs/INSTALL.txt
docs/LICENSE.GPL
docs/LICENSE.txt
ftw/__init__.py
ftw.htmlblock.egg-info/PKG-INFO
ftw.htmlblock.egg-info/SOURCES.txt
ftw.htmlblock.egg-info/dependency_links.txt
ftw.htmlblock.egg-info/entry_points.txt
ftw.htmlblock.egg-info/namespace_packages.txt
ftw.htmlblock.egg-info/not-zip-safe
ftw.htmlblock.egg-info/requires.txt
ftw.htmlblock.egg-info/top_level.txt
ftw/htmlblock/__init__.py
ftw/htmlblock/config.py
ftw/htmlblock/configure.zcml
ftw/htmlblock/lawgiver.zcml
ftw/htmlblock/permissions.zcml
ftw/htmlblock/resources.zcml
ftw/htmlblock/testing.py
ftw/htmlblock/browser/__init__.py
ftw/htmlblock/browser/configure.zcml
ftw/htmlblock/browser/htmlblock.py
ftw/htmlblock/browser/resources/htmlblock-compiled.js
ftw/htmlblock/browser/resources/iframe_check.js
ftw/htmlblock/browser/resources/main.js
ftw/htmlblock/browser/resources/styles.scss
ftw/htmlblock/browser/templates/htmlblock.pt
ftw/htmlblock/contents/__init__.py
ftw/htmlblock/contents/htmlblock.py
ftw/htmlblock/contents/interfaces.py
ftw/htmlblock/locales/ftw.htmlblock.pot
ftw/htmlblock/locales/ftw.lawgiver.pot
ftw/htmlblock/locales/plone.pot
ftw/htmlblock/locales/de/LC_MESSAGES/ftw.htmlblock.po
ftw/htmlblock/locales/de/LC_MESSAGES/ftw.lawgiver.po
ftw/htmlblock/locales/de/LC_MESSAGES/plone.po
ftw/htmlblock/locales/en/LC_MESSAGES/ftw.htmlblock.po
ftw/htmlblock/locales/en/LC_MESSAGES/ftw.lawgiver.po
ftw/htmlblock/locales/en/LC_MESSAGES/plone.po
ftw/htmlblock/profiles/default/jsregistry.xml
ftw/htmlblock/profiles/default/metadata.xml
ftw/htmlblock/profiles/default/propertiestool.xml
ftw/htmlblock/profiles/default/rolemap.xml
ftw/htmlblock/profiles/default/types.xml
ftw/htmlblock/profiles/default/workflows.xml
ftw/htmlblock/profiles/default/types/Plone_Site.xml
ftw/htmlblock/profiles/default/types/ftw.htmlblock.HtmlBlock.xml
ftw/htmlblock/profiles/default/types/ftw.simplelayout.ContentPage.xml
ftw/htmlblock/profiles/default_plone5/metadata.xml
ftw/htmlblock/profiles/default_plone5/registry.xml
ftw/htmlblock/profiles/default_plone5/rolemap.xml
ftw/htmlblock/profiles/default_plone5/types.xml
ftw/htmlblock/profiles/default_plone5/workflows.xml
ftw/htmlblock/profiles/default_plone5/types/Plone_Site.xml
