Metadata-Version: 2.1
Name: ftw.htmlblock
Version: 1.1.3
Summary: A block rendering unescaped HTML to be used on a content page powered by ftw.simplelayout
Home-page: https://github.com/4teamwork/ftw.htmlblock
Author: 4teamwork AG
Author-email: mailto:info@4teamwork.ch
Maintainer: Martin Baechtold
License: GPL2
Keywords: ftw plone html block
Platform: UNKNOWN
Classifier: Framework :: Plone
Classifier: Framework :: Plone :: 4.3
Classifier: Framework :: Plone :: 5.1
Classifier: License :: OSI Approved :: GNU General Public License (GPL)
Classifier: Programming Language :: Python
Classifier: Programming Language :: Python :: 2.7
Classifier: Topic :: Software Development :: Libraries :: Python Modules
Provides-Extra: tests
Provides-Extra: test
